querykit/__init__.py
querykit/apps.py
querykit/base.py
querykit/blocks.py
querykit/default_settings.py
querykit/django.py
querykit/forms.py
querykit/utilities.py
querykit/value_sources.py
querykit/value_types.py
querykit/variable_specifier.py
querykit/static/querykit/css/querykit.css
querykit/templates/querykit/composite_form_panel.html
querykit/templates/querykit/form_panel.html
querykit/templates/querykit/query_form.html
querykit/templates/querykit/result_range_panel.html
querykit/templates/querykit/form_widgets/button.html
querykit/templates/querykit/form_widgets/deletable_label.html
querykit/templates/querykit/form_widgets/picker.html
querykit/templates/querykit/form_widgets/select.html
querykit/templates/querykit/tags/query_result_navigation.html
querykit/templates/querykit/tags/query_result_range.html
querykit/templatetags/__init__.py
querykit/templatetags/querykit_tags.py
querykit-4.1.0.dist-info/AUTHORS.txt
querykit-4.1.0.dist-info/LICENSE.txt
querykit-4.1.0.dist-info/METADATA
querykit-4.1.0.dist-info/WHEEL
querykit-4.1.0.dist-info/top_level.txt
querykit-4.1.0.dist-info/zip-safe
querykit-4.1.0.dist-info/RECORD
